cryptul/__init__.py
cryptul/_cryptul.py
cryptul-0.0.6.dist-info/METADATA
cryptul-0.0.6.dist-info/WHEEL
cryptul-0.0.6.dist-info/top_level.txt
cryptul-0.0.6.dist-info/RECORD
