Metadata-Version: 2.1
Name: cryptul
Version: 0.0.6
Summary: A set of tools for crypto CTFs and more
Author-email: Frollo <fral01@protonmail.com>
Project-URL: Homepage, https://github.com/Frollamma/cryptul/
Project-URL: Bug Tracker, https://github.com/Frollamma/cryptul/issues
Classifier: Programming Language :: Python :: 3
Classifier: License :: OSI Approved :: MIT License
Classifier: Operating System :: OS Independent
Requires-Python: >=3.11
Requires-Dist: pycryptodome >=3.18.0
Requires-Dist: sympy >=1.12
Requires-Dist: factordb-python ==1.3.0
